mcp_server_baidu_digitalhuman/__init__.py
mcp_server_baidu_digitalhuman/dhapi.py
mcp_server_baidu_digitalhuman/dhserver.py
iflow_mcp_mcp_server_baidu_digitalhuman-0.1.3.dist-info/METADATA
iflow_mcp_mcp_server_baidu_digitalhuman-0.1.3.dist-info/WHEEL
iflow_mcp_mcp_server_baidu_digitalhuman-0.1.3.dist-info/entry_points.txt
iflow_mcp_mcp_server_baidu_digitalhuman-0.1.3.dist-info/licenses/LICENSE
iflow_mcp_mcp_server_baidu_digitalhuman-0.1.3.dist-info/RECORD
