Metadata-Version: 2.4
Name: iflow-mcp_mcp-server-baidu-digitalhuman
Version: 0.1.3
Summary: MCP Server Baidu Digital Human
Project-URL: Homepage, https://xiling.cloud.baidu.com
Project-URL: Documentation, https://cloud.baidu.com/doc/AI_DH/index.html
Project-URL: Issues, https://console.bce.baidu.com/support/#/ticket/#/ticket/create
Author: baidu-xiling
Maintainer-email: xiling <xiling_baidu@126.com>
License-Expression: MIT
License-File: LICENSE
Keywords: baidu,digitalhuman,http,mcp
Classifier: Programming Language :: Python
Requires-Python: >=3.12
Requires-Dist: mcp>=1.8.0
